pysus/Notebooks/.gitkeep
pysus/__init__.py
pysus/data/__init__.py
pysus/data/local.py
pysus/dataset/geocode_by_cities.json
pysus/ftp/__init__.py
pysus/ftp/databases/__init__.py
pysus/ftp/databases/ciha.py
pysus/ftp/databases/cnes.py
pysus/ftp/databases/ibge_datasus.py
pysus/ftp/databases/pni.py
pysus/ftp/databases/sia.py
pysus/ftp/databases/sih.py
pysus/ftp/databases/sim.py
pysus/ftp/databases/sinan.py
pysus/ftp/databases/sinasc.py
pysus/ftp/utils.py
pysus/metadata/SINAN/ANIM.tar.gz
pysus/metadata/SINAN/BOTU.tar.gz
pysus/metadata/SINAN/CHAG.tar.gz
pysus/metadata/SINAN/CHIK.tar.gz
pysus/metadata/SINAN/COLE.tar.gz
pysus/metadata/SINAN/COQU.tar.gz
pysus/metadata/SINAN/DENG.tar.gz
pysus/metadata/SINAN/DIFT.tar.gz
pysus/metadata/SINAN/ESQU.tar.gz
pysus/metadata/SINAN/FAMA.tar.gz
pysus/metadata/SINAN/FMAC.tar.gz
pysus/metadata/SINAN/FTIF.tar.gz
pysus/metadata/SINAN/HANS.tar.gz
pysus/metadata/SINAN/HANT.tar.gz
pysus/metadata/SINAN/HEPA.tar.gz
pysus/metadata/SINAN/IEXO.tar.gz
pysus/metadata/SINAN/LEIV.tar.gz
pysus/metadata/SINAN/LEPT.tar.gz
pysus/metadata/SINAN/LTAN.tar.gz
pysus/metadata/SINAN/MALA.tar.gz
pysus/metadata/SINAN/MENI.tar.gz
pysus/metadata/SINAN/PEST.tar.gz
pysus/metadata/SINAN/RAIV.tar.gz
pysus/metadata/SINAN/SIFC.tar.gz
pysus/metadata/SINAN/SIFG.tar.gz
pysus/metadata/SINAN/TETA.tar.gz
pysus/metadata/SINAN/TETN.tar.gz
pysus/metadata/SINAN/TUBE.tar.gz
pysus/metadata/SINAN/typecast.py
pysus/online_data/CIHA.py
pysus/online_data/CNES.py
pysus/online_data/ESUS.py
pysus/online_data/IBGE.py
pysus/online_data/Infodengue.py
pysus/online_data/Infogripe.py
pysus/online_data/PNI.py
pysus/online_data/SIA.py
pysus/online_data/SIH.py
pysus/online_data/SIM.py
pysus/online_data/SINAN.py
pysus/online_data/SINASC.py
pysus/online_data/__init__.py
pysus/online_data/vaccine.py
pysus/preprocessing/ESUS.py
pysus/preprocessing/SIM.py
pysus/preprocessing/__init__.py
pysus/preprocessing/decoders.py
pysus/preprocessing/geodata.py
pysus/preprocessing/sinan.py
pysus/tests/__init__.py
pysus-0.14.0.dist-info/LICENSE
pysus-0.14.0.dist-info/METADATA
pysus-0.14.0.dist-info/WHEEL
pysus-0.14.0.dist-info/RECORD
