Metadata-Version: 2.1
Name: pysus
Version: 0.14.0
Summary: Tools for dealing with Brazil's Public health data
License: GPL
Author: Flavio Codeco Coelho
Author-email: fccoelho@gmail.com
Requires-Python: >=3.10,<3.12
Classifier: License :: Other/Proprietary License
Classifier: Programming Language :: Python :: 3
Classifier: Programming Language :: Python :: 3.10
Classifier: Programming Language :: Python :: 3.11
Provides-Extra: preprocessing
Requires-Dist: Unidecode (>=1.3.6,<2.0.0)
Requires-Dist: aioftp (>=0.21.4,<0.22.0)
Requires-Dist: bigtree (>=0.12.2,<0.13.0)
Requires-Dist: cffi (==1.15.1)
Requires-Dist: dateparser (>=1.1.8,<2.0.0)
Requires-Dist: dbfread (==2.0.7)
Requires-Dist: elasticsearch[preprocessing] (==7.16.2)
Requires-Dist: fastparquet (>=2023.10.1)
Requires-Dist: humanize (>=4.8.0,<5.0.0)
Requires-Dist: loguru (>=0.6.0,<0.7.0)
Requires-Dist: numpy (==1.26.2)
Requires-Dist: pandas (>=2.1.0)
Requires-Dist: pyarrow (>=11.0.0)
Requires-Dist: pycparser (==2.21)
Requires-Dist: pyreaddbc (>=1.1.0)
Requires-Dist: python-dateutil (==2.8.2)
Requires-Dist: tqdm (==4.64.0)
Requires-Dist: typing-extensions (>=4.9.0,<5.0.0)
Requires-Dist: urwid (>=2.1.2,<3.0.0)
Requires-Dist: wget (>=3.2,<4.0)
